<?xml version="1.0" encoding="UTF-8"?>
<root>
  <coefs>
    <version>2</version>
    <dim>2</dim>
    <datH>  1.7646172286894455e+01  7.8745151744807176e+00  2.0623980619787732e+00  8.7793556082526480e-01  4.7521258387263093e-02 -1.6936633359534113e+01 -4.6941915144702708e+00 -6.5775967016247416e-01 -2.3846838548251703e-01  4.0370476824645660e-02  7.0196675347237658e+01  1.9786253087273259e+01  4.8139937525231629e+00  3.5330642807393903e-01  1.1037795127019033e-01 -7.4839700838996759e+00 -1.4593562024515436e-01  6.6535851395114154e-01  1.9295960605506371e-01  8.1122072805191625e-02  6.5219763091693451e+01  2.2036374714348039e+01  5.9339440181919887e+00  1.3245767947105507e+00  1.6773691489667367e-01  3.7248358304446212e+00 -6.2369773718044264e-01 -1.8395230238046892e-01 -7.0249785548152158e-02 -1.5282052458805540e-02  1.5312352385050643e+00  2.8599105972378314e-01 -1.1057746985390896e-01 -7.1258423636396173e-02 -1.7605826889120088e-02  1.3406883761717302e+02  4.2444188559007884e+01  1.1013474890330928e+01  1.9979211768890102e+00  2.3729762477788105e-01 -1.6613500386973758e+01 -6.5212488498133423e+00 -2.4806512307362856e+00 -6.7004972237794347e-01 -1.1395864152299504e-01 -3.6693834827476685e+01 -7.9074835547421847e+00 -7.5378242264159856e-01 -2.0587493609574281e-01  5.2673197582842862e-02 -8.7674060046962950e+01 -2.5578566837926918e+01 -5.6885061436173654e+00 -1.0835503674912159e+00 -1.7767858960379843e-02 -4.7694701511130781e+01 -1.6572203372704497e+01 -5.2934572994374571e+00 -1.1607926357059579e+00 -1.6806169634692353e-01  1.4449475154141035e+02  3.9339203603438136e+01  7.8473290518526557e+00  4.0710452001404618e-01  5.6553398687225219e-02  4.3577261433581207e+01  1.0684572037478146e+01  1.5698286675651503e+00  1.1877935405412902e-01 -5.5164989226150964e-02 -3.8340150727909679e+00 -3.6281794143053792e+00 -1.2440517631844044e+00 -1.9559132780354246e-01  1.7623907838420838e-01  1.1524257399327709e+00  5.9203761837532287e-01  9.2685889996127507e-02  2.9242326539434664e+00  1.8724583103306242e-01 -4.6048227321543045e-01 -1.8776313822446117e-01  1.2258405335815639e+00 -1.1073905626995165e-01 -1.5597605091600569e-01 -5.2299085020567244e-02  1.2714787643246790e+01  4.5300818899251825e+00  1.3108776318439956e+00  2.8364145224151510e-01 -3.3098968072548999e+01 -9.1694967833025984e+00 -1.8782568477164567e+00 -2.5342570756162419e-01 -6.7112741797036136e+01 -2.2648683090459098e+01 -6.1249907854216703e+00 -1.0924206892485178e+00  2.8089544116750824e+02  8.4590783053523751e+01  2.0604623995611878e+01  3.0659202119314908e+00  3.9258237795168633e+01  5.3777078894859267e+00  3.4349486321634093e-01 -2.3296768572518497e-02  1.2396016398280127e+01  4.3450820397990384e+00  1.1913143709300533e+00  2.1268828772101703e-01  1.0664339049760900e+02  2.3518968454601271e+01  3.6616300117430267e+00  1.7880906328569393e-01  4.4963498944737346e+00  8.6180519626393270e-01  4.1352944143514320e-01  1.2815247454919812e-01 -6.5856230320821879e+01 -2.0102841002789155e+01 -4.8099184170012004e+00 -7.7465536260577794e-01  6.6769334991525156e+01  1.6921113371483614e+01  3.2203832361256679e+00  3.5303358166543725e-01  1.1902350862985342e+01  2.7708640934181155e+00  1.1507740324598972e+00  3.5276006350536465e-01  3.1148185306528569e+02  7.2699348050364975e+01  1.1436742883638917e+01  5.4471160122844153e-01</datH>
    <datS>  6.1087760925292969e+01  2.1785196304321289e+01  8.3521966934204102e+00  2.0124814510345459e+00  6.3298553228378296e-01  9.4965212047100067e-02 -4.1729187011718750e+01 -1.5730116844177246e+01 -5.8177113533020020e+00 -1.3983827829360962e+00 -4.1872632503509521e-01 -5.9878475964069366e-02 -8.8975463867187500e+01 -3.2949481964111328e+01 -1.2388448715209961e+01 -3.0344855785369873e+00 -9.7744590044021606e-01 -1.4679385721683502e-01  1.5035095810890198e-01  2.5532152503728867e-02  9.2574611306190491e-02  1.3954392075538635e-01  3.2996460795402527e-02  9.5746414735913277e-03  7.1305217742919922e+00  2.1982686519622803e+00  7.0234680175781250e-01  1.0285808891057968e-01  1.3803373090922832e-02 -2.6992338243871927e-03 -6.2319111824035645e+00 -2.0128681659698486e+00 -8.4684091806411743e-01 -2.3274357616901398e-01 -5.5321596562862396e-02 -7.2713284753262997e-03  1.6523247957229614e+00  2.3123386502265930e-01  8.9952670037746429e-02  2.5266375392675400e-02  6.5150931477546692e-03  1.1323932558298111e-03  2.2261962890625000e+00  7.2663313150405884e-01  3.5676032304763794e-01  2.6443740725517273e-01  5.7960443198680878e-02  1.5593683347105980e-02  6.4311718940734863e+00  2.4777896404266357e+00  1.0214489698410034e+00  2.6766270399093628e-01  6.4042896032333374e-02  8.6800726130604744e-03 -9.1810691833496094e+01 -3.4039539337158203e+01 -1.1783107757568359e+01 -2.9733777046203613e+00 -8.2837843894958496e-01 -1.0017165541648865e-01 -6.4722679138183594e+01 -2.4323776245117188e+01 -8.2359790802001953e+00 -2.0319962501525879e+00 -5.3487861156463623e-01 -5.9964518994092941e-02  1.0470391273498535e+01  3.3342063426971436e+00  1.6865769624710083e+00  4.0489789843559265e-01  1.1381156742572784e-01  1.8741944804787636e-02 -1.4167272949218750e+02 -5.3433284759521484e+01 -1.8179670333862305e+01 -4.6668276786804199e+00 -1.3078001737594604e+00 -1.5716727077960968e-01  7.4922738075256348e+00  2.1411163806915283e+00  1.3828734159469604e+00  2.7627927064895630e-01  9.7207188606262207e-02  1.8474521115422249e-02</datS>
    <sizeH>134</sizeH>
    <sizeS>84</sizeS>
    <inds>Dict{Array{Symbol,N} where N,Array{Int64,1}}([:Ni, :d, :d, :O] =&gt; [83, 84, 85, 86, 87, 88, 89, 90],[:Ni, :s, :Sc, :p, :S] =&gt; [13, 14, 15, 16, 17, 18],[:Ni, :s, :d, :O] =&gt; [75, 76, 77, 78],[:Ni, :d, :p, :O] =&gt; [91, 92, 93, 94],[:Ni, :s, :p, :O] =&gt; [79, 80, 81, 82],[:Sc, :p, :Ni, :s, :H] =&gt; [11, 12, 13, 14, 15],[:Sc, :s, :Ni, :d, :S] =&gt; [19, 20, 21, 22, 23, 24],[:Ni, :p, :Sc, :d, :H] =&gt; [51, 52, 53, 54, 55, 56, 57, 58, 59, 60],[:Sc, :d, :Ni, :p, :H] =&gt; [51, 52, 53, 54, 55, 56, 57, 58, 59, 60],[:Sc, :d, :Ni, :d, :H] =&gt; [21, 22, 23, 24, 25, 26, 27, 28, 29, 30, 31, 32, 33, 34, 35],[:Sc, :p, :Ni, :s, :S] =&gt; [13, 14, 15, 16, 17, 18],[:Sc, :d, :Ni, :s, :H] =&gt; [6, 7, 8, 9, 10],[:Sc, :p, :Ni, :p, :H] =&gt; [61, 62, 63, 64, 65, 66, 67, 68, 69, 70],[:Ni, :d, :s, :O] =&gt; [75, 76, 77, 78],[:Sc, :s, :p, :O] =&gt; [111, 112, 113, 114],[:Ni, :p, :d, :O] =&gt; [91, 92, 93, 94],[:Sc, :s, :Ni, :s, :H] =&gt; [1, 2, 3, 4, 5],[:Ni, :p, :p, :O] =&gt; [95, 96, 97, 98, 99, 100, 101, 102],[:Sc, :d, :p, :O] =&gt; [123, 124, 125, 126],[:Ni, :s, :Sc, :p, :H] =&gt; [11, 12, 13, 14, 15],[:Ni, :d, :Sc, :d, :S] =&gt; [25, 26, 27, 28, 29, 30, 31, 32, 33, 34, 35, 36, 37, 38, 39, 40, 41, 42],[:Sc, :d, :s, :O] =&gt; [107, 108, 109, 110],[:Ni, :p, :Sc, :p, :S] =&gt; [73, 74, 75, 76, 77, 78, 79, 80, 81, 82, 83, 84],[:Sc, :d, :Ni, :d, :S] =&gt; [25, 26, 27, 28, 29, 30, 31, 32, 33, 34, 35, 36, 37, 38, 39, 40, 41, 42],[:Sc, :s, :Ni, :s, :S] =&gt; [1, 2, 3, 4, 5, 6],[:Sc, :p, :Ni, :p, :S] =&gt; [73, 74, 75, 76, 77, 78, 79, 80, 81, 82, 83, 84],[:Sc, :d, :Ni, :s, :S] =&gt; [7, 8, 9, 10, 11, 12],[:Ni, :p, :Sc, :p, :H] =&gt; [61, 62, 63, 64, 65, 66, 67, 68, 69, 70],[:Ni, :p, :Sc, :d, :S] =&gt; [61, 62, 63, 64, 65, 66, 67, 68, 69, 70, 71, 72],[:Sc, :s, :Ni, :p, :H] =&gt; [46, 47, 48, 49, 50],[:Ni, :d, :Sc, :s, :S] =&gt; [19, 20, 21, 22, 23, 24],[:Sc, :s, :d, :O] =&gt; [107, 108, 109, 110],[:Sc, :s, :s, :O] =&gt; [103, 104, 105, 106],[:Ni, :s, :s, :O] =&gt; [71, 72, 73, 74],[:Sc, :p, :p, :O] =&gt; [127, 128, 129, 130, 131, 132, 133, 134],[:Ni, :s, :Sc, :d, :S] =&gt; [7, 8, 9, 10, 11, 12],[:Ni, :d, :Sc, :d, :H] =&gt; [21, 22, 23, 24, 25, 26, 27, 28, 29, 30, 31, 32, 33, 34, 35],[:Sc, :p, :Ni, :d, :S] =&gt; [43, 44, 45, 46, 47, 48, 49, 50, 51, 52, 53, 54],[:Ni, :p, :Sc, :s, :H] =&gt; [46, 47, 48, 49, 50],[:Ni, :d, :Sc, :p, :H] =&gt; [36, 37, 38, 39, 40, 41, 42, 43, 44, 45],[:Sc, :s, :Ni, :p, :S] =&gt; [55, 56, 57, 58, 59, 60],[:Sc, :d, :d, :O] =&gt; [115, 116, 117, 118, 119, 120, 121, 122],[:Ni, :d, :Sc, :s, :H] =&gt; [16, 17, 18, 19, 20],[:Ni, :p, :s, :O] =&gt; [79, 80, 81, 82],[:Ni, :d, :Sc, :p, :S] =&gt; [43, 44, 45, 46, 47, 48, 49, 50, 51, 52, 53, 54],[:Sc, :s, :Ni, :d, :H] =&gt; [16, 17, 18, 19, 20],[:Sc, :p, :Ni, :d, :H] =&gt; [36, 37, 38, 39, 40, 41, 42, 43, 44, 45],[:Ni, :p, :Sc, :s, :S] =&gt; [55, 56, 57, 58, 59, 60],[:Sc, :p, :s, :O] =&gt; [111, 112, 113, 114],[:Ni, :s, :Sc, :d, :H] =&gt; [6, 7, 8, 9, 10],[:Ni, :s, :Sc, :s, :S] =&gt; [1, 2, 3, 4, 5, 6],[:Sc, :d, :Ni, :p, :S] =&gt; [61, 62, 63, 64, 65, 66, 67, 68, 69, 70, 71, 72],[:Ni, :s, :Sc, :s, :H] =&gt; [1, 2, 3, 4, 5],[:Sc, :p, :d, :O] =&gt; [123, 124, 125, 126])</inds>
    <names>Ni  Sc  </names>
    <cutoff>18.01</cutoff>
    <min_dist>2.97754510000803</min_dist>
    <maxmin_val_train>[:Ni, :d, :d, :O] =&gt; (1.0e7, -1.0e7)
[:Ni, :s, :Sc, :p, :S] =&gt; (1.0e7, -1.0e7)
[:Ni, :s, :d, :O] =&gt; (1.0e7, -1.0e7)
[:Ni, :d, :p, :O] =&gt; (1.0e7, -1.0e7)
[:Ni, :s, :p, :O] =&gt; (1.0e7, -1.0e7)
[:Sc, :p, :Ni, :s, :H] =&gt; (1.0e7, -1.0e7)
[:Sc, :s, :Ni, :d, :S] =&gt; (1.0e7, -1.0e7)
[:Ni, :p, :Sc, :d, :H] =&gt; (1.0e7, -1.0e7)
[:Sc, :d, :Ni, :p, :H] =&gt; (1.0e7, -1.0e7)
[:Sc, :d, :Ni, :d, :H] =&gt; (1.0e7, -1.0e7)
[:Sc, :p, :Ni, :s, :S] =&gt; (1.0e7, -1.0e7)
[:Sc, :d, :Ni, :s, :H] =&gt; (1.0e7, -1.0e7)
[:Sc, :p, :Ni, :p, :H] =&gt; (1.0e7, -1.0e7)
[:Ni, :d, :s, :O] =&gt; (1.0e7, -1.0e7)
[:Sc, :s, :p, :O] =&gt; (1.0e7, -1.0e7)
[:Ni, :p, :d, :O] =&gt; (1.0e7, -1.0e7)
[:Sc, :s, :Ni, :s, :H] =&gt; (1.0e7, -1.0e7)
[:Ni, :p, :p, :O] =&gt; (1.0e7, -1.0e7)
[:Sc, :d, :p, :O] =&gt; (1.0e7, -1.0e7)
[:Ni, :s, :Sc, :p, :H] =&gt; (1.0e7, -1.0e7)
[:Ni, :d, :Sc, :d, :S] =&gt; (1.0e7, -1.0e7)
[:Sc, :d, :s, :O] =&gt; (1.0e7, -1.0e7)
[:Ni, :p, :Sc, :p, :S] =&gt; (1.0e7, -1.0e7)
[:Sc, :d, :Ni, :d, :S] =&gt; (1.0e7, -1.0e7)
[:Sc, :s, :Ni, :s, :S] =&gt; (1.0e7, -1.0e7)
[:Sc, :p, :Ni, :p, :S] =&gt; (1.0e7, -1.0e7)
[:Sc, :d, :Ni, :s, :S] =&gt; (1.0e7, -1.0e7)
[:Ni, :p, :Sc, :p, :H] =&gt; (1.0e7, -1.0e7)
[:Ni, :p, :Sc, :d, :S] =&gt; (1.0e7, -1.0e7)
[:Sc, :s, :Ni, :p, :H] =&gt; (1.0e7, -1.0e7)
[:Ni, :d, :Sc, :s, :S] =&gt; (1.0e7, -1.0e7)
[:Sc, :s, :d, :O] =&gt; (1.0e7, -1.0e7)
[:Sc, :s, :s, :O] =&gt; (1.0e7, -1.0e7)
[:Ni, :s, :s, :O] =&gt; (1.0e7, -1.0e7)
[:Sc, :p, :p, :O] =&gt; (1.0e7, -1.0e7)
[:Ni, :s, :Sc, :d, :S] =&gt; (1.0e7, -1.0e7)
[:Ni, :d, :Sc, :d, :H] =&gt; (1.0e7, -1.0e7)
[:Sc, :p, :Ni, :d, :S] =&gt; (1.0e7, -1.0e7)
[:Ni, :p, :Sc, :s, :H] =&gt; (1.0e7, -1.0e7)
[:Ni, :d, :Sc, :p, :H] =&gt; (1.0e7, -1.0e7)
[:Sc, :s, :Ni, :p, :S] =&gt; (1.0e7, -1.0e7)
[:Sc, :d, :d, :O] =&gt; (1.0e7, -1.0e7)
[:Ni, :d, :Sc, :s, :H] =&gt; (1.0e7, -1.0e7)
[:Ni, :p, :s, :O] =&gt; (1.0e7, -1.0e7)
[:Ni, :d, :Sc, :p, :S] =&gt; (1.0e7, -1.0e7)
[:Sc, :s, :Ni, :d, :H] =&gt; (1.0e7, -1.0e7)
[:Sc, :p, :Ni, :d, :H] =&gt; (1.0e7, -1.0e7)
[:Ni, :p, :Sc, :s, :S] =&gt; (1.0e7, -1.0e7)
[:Sc, :p, :s, :O] =&gt; (1.0e7, -1.0e7)
[:Ni, :s, :Sc, :d, :H] =&gt; (1.0e7, -1.0e7)
[:Ni, :s, :Sc, :s, :S] =&gt; (1.0e7, -1.0e7)
[:Sc, :d, :Ni, :p, :S] =&gt; (1.0e7, -1.0e7)
[:Ni, :s, :Sc, :s, :H] =&gt; (1.0e7, -1.0e7)
[:Sc, :p, :d, :O] =&gt; (1.0e7, -1.0e7)
</maxmin_val_train>
    <dist_frontier>(:Sc, :Ni) =&gt; 2.97754510000803
(:Ni, :Ni) =&gt; 3.2740364999999994
(:Ni, :Sc) =&gt; 2.97754510000803
(:Sc, :Sc) =&gt; 3.6722174999999995
</dist_frontier>
  </coefs>
</root>
