<?xml version="1.0" encoding="UTF-8"?>
<root>
  <coefs>
    <version>2</version>
    <dim>2</dim>
    <datH> -9.6769614521858884e+01 -2.3219886468786193e+01 -5.8171892017380662e+00 -1.0397132313757567e+00 -9.3087921558582851e-02  8.3634091231699870e+01  2.4129132940520392e+01  6.8867068440524513e+00  1.4034124093708875e+00  1.2471369886097039e-01  1.1109687860722516e+02  3.0484692267211205e+01  9.5899142703683076e+00  2.0362757173846102e+00  1.3570975997721388e-01  1.5432546231907997e+02  4.9418907608378646e+01  1.4531816380098736e+01  2.9155417069312382e+00  3.7628979206238400e-01 -2.3443951993840713e+01 -5.4938667515274293e+00 -1.8581146731639862e+00 -5.3204073365140792e-01 -1.0796805175791285e-01 -2.5422458587715436e+01 -7.1696681755884342e+00 -1.8111916772634848e+00 -3.1507552412932721e-01  8.7114724476051521e+01  2.1679694338159681e+01  4.2867195566618133e+00  6.0229675118098158e-01  1.0718247554054122e+01  3.1686804392893908e+00  7.8739680493238418e-01  1.4087243646316169e-01  2.2374530648172097e+01  5.3959924145217428e+00  5.1417940540730711e-01 -1.5508247095141056e-01  1.8280061689252445e+01  6.2126895220616163e+00  1.7455169627794702e+00  3.0167457364196121e-01  1.2576199884792949e+02  3.3716653098788839e+01  7.3556543660694063e+00  1.0213100703167075e+00  1.9069998236699817e+01  5.0076837150371540e+00  1.0558483081859007e+00  1.4258357972117125e-01 -4.0480458481625860e+01 -1.0163267323518500e+01 -2.0571876905419675e+00 -2.3838181536378888e-01</datH>
    <datS> -2.9691646099090576e+00 -1.9160989522933960e+00 -3.2364478707313538e-01 -2.2226730361580849e-02  3.1785948667675257e-03  9.3331391690298915e-04 -1.2069293856620789e-01  8.9613132178783417e-02 -5.1577681303024292e-01 -1.5726993978023529e-01 -3.0982514843344688e-02 -3.8122304249554873e-03 -2.2258665561676025e+00 -1.6893550753593445e-01 -8.9638024568557739e-01 -2.4599327147006989e-01 -5.5694863200187683e-02 -1.0242500342428684e-02 -1.4421201705932617e+01 -5.8832345008850098e+00 -2.6016349792480469e+00 -5.5536353588104248e-01 -1.3142347335815430e-01 -1.9885336980223656e-02  8.6745369434356689e-01 -4.3227872252464294e-01  9.0279132127761841e-02  2.5069134309887886e-02  5.6185950525105000e-03  1.1190964141860604e-03</datS>
    <sizeH>57</sizeH>
    <sizeS>30</sizeS>
    <inds>Dict{Array{Symbol,N} where N,Array{Int64,1}}([:F, :s, :p, :O] =&gt; [46, 47, 48, 49],[:Bi, :p, :p, :O] =&gt; [34, 35, 36, 37, 38, 39, 40, 41],[:F, :p, :p, :O] =&gt; [50, 51, 52, 53, 54, 55, 56, 57],[:F, :p, :Bi, :p, :H] =&gt; [16, 17, 18, 19, 20, 21, 22, 23, 24, 25],[:F, :p, :Bi, :s, :H] =&gt; [6, 7, 8, 9, 10],[:F, :s, :s, :O] =&gt; [42, 43, 44, 45],[:F, :p, :Bi, :p, :S] =&gt; [19, 20, 21, 22, 23, 24, 25, 26, 27, 28, 29, 30],[:F, :p, :s, :O] =&gt; [46, 47, 48, 49],[:Bi, :p, :F, :s, :S] =&gt; [13, 14, 15, 16, 17, 18],[:F, :s, :Bi, :s, :H] =&gt; [1, 2, 3, 4, 5],[:Bi, :p, :F, :p, :S] =&gt; [19, 20, 21, 22, 23, 24, 25, 26, 27, 28, 29, 30],[:Bi, :s, :s, :O] =&gt; [26, 27, 28, 29],[:Bi, :p, :F, :s, :H] =&gt; [11, 12, 13, 14, 15],[:Bi, :p, :s, :O] =&gt; [30, 31, 32, 33],[:Bi, :p, :F, :p, :H] =&gt; [16, 17, 18, 19, 20, 21, 22, 23, 24, 25],[:Bi, :s, :p, :O] =&gt; [30, 31, 32, 33],[:F, :s, :Bi, :s, :S] =&gt; [1, 2, 3, 4, 5, 6],[:F, :p, :Bi, :s, :S] =&gt; [7, 8, 9, 10, 11, 12],[:Bi, :s, :F, :p, :S] =&gt; [7, 8, 9, 10, 11, 12],[:F, :s, :Bi, :p, :H] =&gt; [11, 12, 13, 14, 15],[:F, :s, :Bi, :p, :S] =&gt; [13, 14, 15, 16, 17, 18],[:Bi, :s, :F, :s, :H] =&gt; [1, 2, 3, 4, 5],[:Bi, :s, :F, :p, :H] =&gt; [6, 7, 8, 9, 10],[:Bi, :s, :F, :s, :S] =&gt; [1, 2, 3, 4, 5, 6])</inds>
    <names>F  Bi  </names>
    <cutoff>18.01</cutoff>
    <min_dist>3.062475864508194</min_dist>
    <maxmin_val_train>[:F, :s, :p, :O] =&gt; (1.0e7, -1.0e7)
[:Bi, :p, :p, :O] =&gt; (1.0e7, -1.0e7)
[:F, :p, :p, :O] =&gt; (1.0e7, -1.0e7)
[:F, :p, :Bi, :p, :H] =&gt; (1.0e7, -1.0e7)
[:F, :p, :Bi, :s, :H] =&gt; (1.0e7, -1.0e7)
[:F, :s, :s, :O] =&gt; (1.0e7, -1.0e7)
[:F, :p, :Bi, :p, :S] =&gt; (1.0e7, -1.0e7)
[:F, :p, :s, :O] =&gt; (1.0e7, -1.0e7)
[:Bi, :p, :F, :s, :S] =&gt; (1.0e7, -1.0e7)
[:F, :s, :Bi, :s, :H] =&gt; (1.0e7, -1.0e7)
[:Bi, :p, :F, :p, :S] =&gt; (1.0e7, -1.0e7)
[:Bi, :s, :s, :O] =&gt; (1.0e7, -1.0e7)
[:Bi, :p, :F, :s, :H] =&gt; (1.0e7, -1.0e7)
[:Bi, :p, :s, :O] =&gt; (1.0e7, -1.0e7)
[:Bi, :p, :F, :p, :H] =&gt; (1.0e7, -1.0e7)
[:Bi, :s, :p, :O] =&gt; (1.0e7, -1.0e7)
[:F, :s, :Bi, :s, :S] =&gt; (1.0e7, -1.0e7)
[:F, :p, :Bi, :s, :S] =&gt; (1.0e7, -1.0e7)
[:Bi, :s, :F, :p, :S] =&gt; (1.0e7, -1.0e7)
[:F, :s, :Bi, :p, :H] =&gt; (1.0e7, -1.0e7)
[:F, :s, :Bi, :p, :S] =&gt; (1.0e7, -1.0e7)
[:Bi, :s, :F, :s, :H] =&gt; (1.0e7, -1.0e7)
[:Bi, :s, :F, :p, :H] =&gt; (1.0e7, -1.0e7)
[:Bi, :s, :F, :s, :S] =&gt; (1.0e7, -1.0e7)
</maxmin_val_train>
    <dist_frontier>(:F, :Bi) =&gt; 3.062475864508194
(:Bi, :F) =&gt; 3.062475864508194
(:Bi, :Bi) =&gt; 4.167932999999998
(:F, :F) =&gt; 2.546339999999999
</dist_frontier>
  </coefs>
</root>
