<?xml version="1.0" encoding="UTF-8"?>
<root>
  <coefs>
    <version>2</version>
    <dim>3</dim>
    <datH> -5.3392508912652832e-03 -1.7371774583364573e-04  8.6863796649593272e-01 -1.1449963633548185e-01 -8.7642440957275709e-03 -6.7038069817908730e-01  5.9002701048703921e-01  4.4760949166935668e-02 -1.4653853031381028e+00  6.0814003504861580e-01  5.2452593182342112e-02  3.6980410300870501e+00  2.7679668568951665e-01  2.7115220813876281e-02  7.1828958928591091e-01 -1.1094611354704274e+00 -9.2851607234690561e-02  5.4860072246024028e-01  7.4072873476346224e-02  9.7025988561905765e-03 -3.7237681805063181e+00 -1.5966855186434392e-01 -2.3997171868665165e-02 -1.2684712364486504e+01  1.1384318592288656e-01  3.2274437526758376e-02  3.0868971623908823e+01  1.5766512093165688e-01  3.4389314030730776e-02 -2.9059832892432639e-03 -4.2366468847273919e-01  4.2162364106070903e-02 -4.2110169030593753e-03  1.2901424607215627e-02 -1.5743288551216044e+00 -4.1242015839703877e-01 -4.5553596341095001e-02 -2.8152562814292671e-02  1.9040967607093480e+00 -4.7801167803776035e-01 -4.2134148886207569e-02 -3.6444051431624047e-02  4.4669708150805363e+00 -2.3022842664479876e-01 -1.2106673042399820e-02 -3.2022554660699164e-02  1.6698309829965141e+00  5.6887348129206872e-01  7.8792170051327035e-02  2.2210187948707830e-02 -2.2719167099277211e+00  3.3593947288292891e-01  3.5441669592537382e-02  1.2320072142108666e-02 -7.4477912408369773e-01  1.1718128740929940e-01  1.3898759911867731e-02 -1.1116894644285832e-03  3.3056804093253073e-01 -6.5464547733764122e-01 -4.4232837911936232e-02 -4.4052914247958576e-02  1.0443134056802066e+01 -8.9461236544855527e-01 -7.6882967217235976e-02 -4.3965401864751598e-02  6.9066094615168598e+00 -8.4508258447680706e-01 -3.6915993665114402e-02 -9.1165353381813016e-02 -6.3544205359465766e-01  9.4953519676602127e-01  1.4081661600774714e-01  1.0283490614611349e-02 -6.5079980718293449e+00  1.2660492657424932e+01 -1.2583810260555875e-01  2.7793466884788320e+00 -9.6773450338485736e-03 -6.4588364087711836e-01 -6.8555768127212247e-01 -3.4399208090469580e-01  8.8358656086991638e-01  1.8470791087373146e+00 -2.1848766268986286e-01  9.2594037954884811e-01 -3.9161133461447532e-03 -5.6045946358020859e-01 -1.4249783595141203e+00 -6.0404418894720135e-01  1.8838018551201414e+00</datH>
    <datS></datS>
    <sizeH>91</sizeH>
    <sizeS>0</sizeS>
    <inds>Dict{Array{Symbol,N} where N,Array{Int64,1}}([:P, :s, :P, :p, :Pt, :H] =&gt; [4, 5, 6],[:P, :p, :Pt, :p, :Pt, :H] =&gt; [72, 73, 74, 75],[:Pt, :p, :Pt, :d, :P, :H] =&gt; [22, 23, 24],[:P, :s, :Pt, :s, :Pt, :H] =&gt; [52, 53, 54, 55],[:P, :s, :Pt, :d, :P, :H] =&gt; [32, 33, 34, 35],[:Pt, :d, :Pt, :d, :P, :H] =&gt; [19, 20, 21],[:P, :Pt, :P, :O] =&gt; [80, 82, 81, 83],[:P, :p, :Pt, :s, :Pt, :H] =&gt; [64, 65, 66, 67],[:P, :p, :Pt, :d, :Pt, :H] =&gt; [68, 69, 70, 71],[:Pt, :d, :Pt, :s, :P, :H] =&gt; [13, 14, 15],[:Pt, :s, :Pt, :s, :P, :H] =&gt; [10, 11, 12],[:P, :s, :Pt, :d, :Pt, :H] =&gt; [56, 57, 58, 59],[:Pt, :d, :P, :s, :P, :H] =&gt; [32, 34, 33, 35],[:P, :p, :Pt, :p, :P, :H] =&gt; [48, 49, 50, 51],[:Pt, :d, :Pt, :p, :P, :H] =&gt; [22, 23, 24],[:P, :p, :P, :p, :Pt, :H] =&gt; [7, 8, 9],[:Pt, :s, :Pt, :d, :P, :H] =&gt; [13, 14, 15],[:P, :s, :Pt, :s, :P, :H] =&gt; [28, 29, 30, 31],[:Pt, :p, :P, :p, :P, :H] =&gt; [48, 50, 49, 51],[:Pt, :d, :P, :p, :Pt, :H] =&gt; [68, 70, 69, 71],[:P, :p, :P, :s, :Pt, :H] =&gt; [4, 5, 6],[:P, :p, :Pt, :d, :P, :H] =&gt; [44, 45, 46, 47],[:Pt, :p, :P, :s, :P, :H] =&gt; [36, 38, 37, 39],[:P, :s, :Pt, :p, :Pt, :H] =&gt; [60, 61, 62, 63],[:Pt, :p, :Pt, :s, :P, :H] =&gt; [16, 17, 18],[:P, :s, :Pt, :p, :P, :H] =&gt; [36, 37, 38, 39],[:Pt, :p, :P, :p, :Pt, :H] =&gt; [72, 74, 73, 75],[:P, :s, :P, :s, :Pt, :H] =&gt; [1, 2, 3],[:Pt, :d, :P, :p, :P, :H] =&gt; [44, 46, 45, 47],[:Pt, :p, :P, :s, :Pt, :H] =&gt; [60, 62, 61, 63],[:Pt, :d, :P, :s, :Pt, :H] =&gt; [56, 58, 57, 59],[:Pt, :P, :Pt, :O] =&gt; [88, 89, 90, 91],[:P, :P, :Pt, :O] =&gt; [80, 81, 82, 83],[:Pt, :s, :P, :p, :Pt, :H] =&gt; [64, 66, 65, 67],[:Pt, :p, :Pt, :p, :P, :H] =&gt; [25, 26, 27],[:Pt, :s, :P, :p, :P, :H] =&gt; [40, 42, 41, 43],[:Pt, :s, :Pt, :p, :P, :H] =&gt; [16, 17, 18],[:P, :p, :Pt, :s, :P, :H] =&gt; [40, 41, 42, 43],[:P, :Pt, :Pt, :O] =&gt; [76, 77, 78, 79],[:Pt, :P, :P, :O] =&gt; [84, 85, 86, 87],[:Pt, :Pt, :P, :O] =&gt; [88, 90, 89, 91],[:Pt, :s, :P, :s, :Pt, :H] =&gt; [52, 54, 53, 55],[:Pt, :s, :P, :s, :P, :H] =&gt; [28, 30, 29, 31])</inds>
    <names>Pt  P  </names>
    <cutoff>18.01</cutoff>
    <min_dist>3.1641667573519077</min_dist>
    <maxmin_val_train>[:P, :s, :P, :p, :Pt, :H] =&gt; (1.0e7, -1.0e7)
[:P, :p, :Pt, :p, :Pt, :H] =&gt; (1.0e7, -1.0e7)
[:Pt, :p, :Pt, :d, :P, :H] =&gt; (1.0e7, -1.0e7)
[:P, :s, :Pt, :s, :Pt, :H] =&gt; (1.0e7, -1.0e7)
[:P, :s, :Pt, :d, :P, :H] =&gt; (1.0e7, -1.0e7)
[:Pt, :d, :Pt, :d, :P, :H] =&gt; (1.0e7, -1.0e7)
[:P, :Pt, :P, :O] =&gt; (1.0e7, -1.0e7)
[:P, :p, :Pt, :s, :Pt, :H] =&gt; (1.0e7, -1.0e7)
[:P, :p, :Pt, :d, :Pt, :H] =&gt; (1.0e7, -1.0e7)
[:Pt, :d, :Pt, :s, :P, :H] =&gt; (1.0e7, -1.0e7)
[:Pt, :s, :Pt, :s, :P, :H] =&gt; (1.0e7, -1.0e7)
[:P, :s, :Pt, :d, :Pt, :H] =&gt; (1.0e7, -1.0e7)
[:Pt, :d, :P, :s, :P, :H] =&gt; (1.0e7, -1.0e7)
[:P, :p, :Pt, :p, :P, :H] =&gt; (1.0e7, -1.0e7)
[:Pt, :d, :Pt, :p, :P, :H] =&gt; (1.0e7, -1.0e7)
[:P, :p, :P, :p, :Pt, :H] =&gt; (1.0e7, -1.0e7)
[:Pt, :s, :Pt, :d, :P, :H] =&gt; (1.0e7, -1.0e7)
[:P, :s, :Pt, :s, :P, :H] =&gt; (1.0e7, -1.0e7)
[:Pt, :p, :P, :p, :P, :H] =&gt; (1.0e7, -1.0e7)
[:Pt, :d, :P, :p, :Pt, :H] =&gt; (1.0e7, -1.0e7)
[:P, :p, :P, :s, :Pt, :H] =&gt; (1.0e7, -1.0e7)
[:P, :p, :Pt, :d, :P, :H] =&gt; (1.0e7, -1.0e7)
[:Pt, :p, :P, :s, :P, :H] =&gt; (1.0e7, -1.0e7)
[:P, :s, :Pt, :p, :Pt, :H] =&gt; (1.0e7, -1.0e7)
[:Pt, :p, :Pt, :s, :P, :H] =&gt; (1.0e7, -1.0e7)
[:P, :s, :Pt, :p, :P, :H] =&gt; (1.0e7, -1.0e7)
[:Pt, :p, :P, :p, :Pt, :H] =&gt; (1.0e7, -1.0e7)
[:P, :s, :P, :s, :Pt, :H] =&gt; (1.0e7, -1.0e7)
[:Pt, :d, :P, :p, :P, :H] =&gt; (1.0e7, -1.0e7)
[:Pt, :p, :P, :s, :Pt, :H] =&gt; (1.0e7, -1.0e7)
[:Pt, :d, :P, :s, :Pt, :H] =&gt; (1.0e7, -1.0e7)
[:Pt, :P, :Pt, :O] =&gt; (1.0e7, -1.0e7)
[:P, :P, :Pt, :O] =&gt; (1.0e7, -1.0e7)
[:Pt, :s, :P, :p, :Pt, :H] =&gt; (1.0e7, -1.0e7)
[:Pt, :p, :Pt, :p, :P, :H] =&gt; (1.0e7, -1.0e7)
[:Pt, :s, :P, :p, :P, :H] =&gt; (1.0e7, -1.0e7)
[:Pt, :s, :Pt, :p, :P, :H] =&gt; (1.0e7, -1.0e7)
[:P, :p, :Pt, :s, :P, :H] =&gt; (1.0e7, -1.0e7)
[:P, :Pt, :Pt, :O] =&gt; (1.0e7, -1.0e7)
[:Pt, :P, :P, :O] =&gt; (1.0e7, -1.0e7)
[:Pt, :Pt, :P, :O] =&gt; (1.0e7, -1.0e7)
[:Pt, :s, :P, :s, :Pt, :H] =&gt; (1.0e7, -1.0e7)
[:Pt, :s, :P, :s, :P, :H] =&gt; (1.0e7, -1.0e7)
</maxmin_val_train>
    <dist_frontier>(:Pt, :Pt, :Pt) =&gt; [[6.5729721068, 4.647793149268308, 4.647793149268308], [4.647793149268308, 4.647793149268308, 6.5729721068], [4.647793149268308, 4.70241513643387, 4.70241513643387], [4.70241513643387, 4.647793149268308, 4.70241513643387], [6.928385084847147, 4.3015632892, 5.431304921742037], [5.431304921742037, 4.3015632892, 6.928385084847147], [4.3015632892, 5.431304921742037, 6.928385084847147], [7.380380322855776, 4.261064565675025, 4.261064565707227], [4.261064565707227, 4.261064565675025, 7.380380322855776], [6.41451426, 3.643804499999999, 7.377215221610631], [9.10951125, 3.643804499999999, 5.465706750000002], [7.377215221610631, 3.643804499999999, 6.41451426], [3.643804499999999, 6.41451426, 7.377215221610631], [3.643804499999999, 5.465706750000002, 9.10951125], [5.465706750000002, 3.643804499999999, 9.10951125]]
(:Pt, :P, :P) =&gt; [[10.447311426734862, 3.024287692529401, 10.0], [3.240040886027862, 3.240040886027862, 3.012418499999999], [3.2072571300000003, 4.400132215863302, 3.0124185000000003], [4.400132215863302, 3.2072571300000003, 3.0124185000000003]]
(:Pt, :P, :Pt) =&gt; [[10.447311426734862, 10.0, 3.024287692529401], [3.3983122939043895, 3.643804499999999, 3.3983122939043895], [4.558987084985603, 7.171644964, 3.240040886027862], [3.240040886027862, 7.171644964, 4.558987084985603], [3.2072571300000003, 8.018142825, 4.810885695], [3.2072571300000003, 3.6438045000000003, 4.854256846537489], [4.810885695, 8.018142825, 3.2072571300000003], [4.854256846537489, 3.6438045000000003, 3.2072571300000003]]
(:P, :P, :P) =&gt; [[5.180330335898196, 4.488663036696383, 4.488663036696383], [4.488663036696383, 4.488663036696383, 5.180330335898196], [4.946946202284344, 4.505919205227075, 4.516326940231825], [4.505919205227075, 4.516326940231825, 4.946946202284344], [4.516326940231825, 4.505919205227075, 4.946946202284344], [5.333826528476746, 3.5611593839864994, 3.627233891294431], [5.37528555081955, 3.5611593839864994, 3.6268586652954906], [3.627233891294431, 3.5611593839864994, 5.333826528476746], [3.6268586652954906, 3.5611593839864994, 5.37528555081955], [3.5611593839864994, 3.6268586652954906, 5.37528555081955], [3.5611593839864994, 3.627233891294431, 5.333826528476746], [5.200966118921154, 4.373993320349357, 4.611284685299599], [4.611284685299599, 4.373993320349357, 5.200966118921154], [4.373993320349357, 4.611284685299599, 5.200966118921154], [6.0, 3.398231662, 6.895504218591943], [6.895504218591943, 3.398231662, 6.0], [3.398231662, 6.0, 6.895504218591943], [6.41451426, 3.012418499999999, 7.086653541050641], [7.53104625, 3.012418499999999, 4.518627750000001], [7.086653541050641, 3.012418499999999, 6.41451426], [3.012418499999999, 6.41451426, 7.086653541050641], [3.012418499999999, 4.518627750000001, 7.53104625], [4.518627750000001, 3.012418499999999, 7.53104625]]
(:Pt, :Pt, :P) =&gt; [[3.643804499999999, 3.3983122939043895, 3.3983122939043895], [7.171644964, 3.240040886027862, 4.558987084985603], [8.018142825, 3.2072571300000003, 4.810885695], [3.6438045000000003, 3.2072571300000003, 4.854256846537489]]
(:P, :P, :Pt) =&gt; [[3.012418499999999, 3.240040886027862, 3.240040886027862], [3.0124185000000003, 3.2072571300000003, 4.400132215863302]]
(:P, :Pt, :Pt) =&gt; [[10.447311426734862, 3.024287692529401, 10.0], [3.3983122939043895, 3.3983122939043895, 3.643804499999999], [3.240040886027862, 4.558987084985603, 7.171644964], [4.558987084985603, 3.240040886027862, 7.171644964], [4.810885695, 3.2072571300000003, 8.018142825], [3.2072571300000003, 4.810885695, 8.018142825], [3.2072571300000003, 4.854256846537489, 3.6438045000000003], [4.854256846537489, 3.2072571300000003, 3.6438045000000003]]
(:P, :Pt, :P) =&gt; [[10.447311426734862, 10.0, 3.024287692529401], [3.240040886027862, 3.012418499999999, 3.240040886027862], [3.2072571300000003, 3.0124185000000003, 4.400132215863302], [4.400132215863302, 3.0124185000000003, 3.2072571300000003]]
</dist_frontier>
  </coefs>
</root>
